calyxos/__init__.py
calyxos/core/__init__.py
calyxos/core/async_support.py
calyxos/core/decorator.py
calyxos/core/introspection.py
calyxos/core/markers.py
calyxos/core/persistence.py
calyxos/graph/__init__.py
calyxos/graph/graph.py
calyxos/graph/node.py
calyxos/ml/__init__.py
calyxos/ml/tensor_memoization.py
calyxos/storage/__init__.py
calyxos/storage/backend.py
calyxos/storage/json_storage.py
calyxos/storage/sqlite.py
calyxos/tracking/__init__.py
calyxos/tracking/context.py
calyxos/utils/__init__.py
calyxos/utils/debug.py
calyxos/utils/distributed.py
calyxos/utils/gradient_tracking.py
calyxos/utils/profiler.py
calyxos-0.1.1.dist-info/METADATA
calyxos-0.1.1.dist-info/WHEEL
calyxos-0.1.1.dist-info/licenses/LICENSE
calyxos-0.1.1.dist-info/RECORD
