Metadata-Version: 2.4
Name: calyxos
Version: 0.1.1
Summary: Reactive object computation framework with memoized, dependency-aware nodes
Project-URL: Homepage, https://github.com/krish-shahh/calyxos
Project-URL: Repository, https://github.com/krish-shahh/calyxos
Project-URL: Issues, https://github.com/krish-shahh/calyxos/issues
Project-URL: Documentation, https://github.com/krish-shahh/calyxos/blob/main/README.md
Author: Krish Shah
License: MIT
License-File: LICENSE
Keywords: computation,dag,dependency-tracking,llm,memoization,ml,reactive
Classifier: Development Status :: 4 - Beta
Classifier: Intended Audience :: Developers
Classifier: License :: OSI Approved :: MIT License
Classifier: Programming Language :: Python :: 3
Classifier: Programming Language :: Python :: 3.10
Classifier: Programming Language :: Python :: 3.11
Classifier: Programming Language :: Python :: 3.12
Classifier: Topic :: Software Development :: Libraries
Requires-Python: >=3.10
Provides-Extra: dev
Requires-Dist: black>=23.9.0; extra == 'dev'
Requires-Dist: mypy>=1.5.0; extra == 'dev'
Requires-Dist: pytest-cov>=4.1.0; extra == 'dev'
Requires-Dist: pytest>=7.4.0; extra == 'dev'
Requires-Dist: ruff>=0.1.0; extra == 'dev'
